my_portfolio_analysis/__init__.py
my_portfolio_analysis/my_inv_analysis_xalpha.py
tests/__init__.py
tests/month_end_closing_20220323.xlsx
tests/report.xlsx
tests/test_my_inv_analysis_xalpha.py
tests/my_inv_record/Inv_Asset_Record.xlsx
my_portfolio_analysis-0.1.1.dist-info/LICENSE
my_portfolio_analysis-0.1.1.dist-info/METADATA
my_portfolio_analysis-0.1.1.dist-info/WHEEL
my_portfolio_analysis-0.1.1.dist-info/top_level.txt
my_portfolio_analysis-0.1.1.dist-info/RECORD
