Metadata-Version: 2.1
Name: my-portfolio-analysis
Version: 0.1.1
Summary: UNKNOWN
Home-page: https://github.com/laye0619/my_portfolio_analysis
Author: LayeWang
Author-email: laye0619@gmail.com
License: UNKNOWN
Platform: UNKNOWN
Classifier: Programming Language :: Python :: 3
Classifier: License :: OSI Approved :: MIT License
Classifier: Operating System :: OS Independent
License-File: LICENSE
Requires-Dist: xalpha
Requires-Dist: pandas
Requires-Dist: openpyxl
